blockdiagcontrib_eps-0.1.1-py2.7-nspkg.pth
blockdiagcontrib/eps.py
blockdiagcontrib_eps-0.1.1.dist-info/DESCRIPTION.rst
blockdiagcontrib_eps-0.1.1.dist-info/entry_points.txt
blockdiagcontrib_eps-0.1.1.dist-info/METADATA
blockdiagcontrib_eps-0.1.1.dist-info/metadata.json
blockdiagcontrib_eps-0.1.1.dist-info/namespace_packages.txt
blockdiagcontrib_eps-0.1.1.dist-info/RECORD
blockdiagcontrib_eps-0.1.1.dist-info/top_level.txt
blockdiagcontrib_eps-0.1.1.dist-info/WHEEL
