Metadata-Version: 2.0
Name: blockdiagcontrib-eps
Version: 0.1.1
Summary: EPS imagedrawer plugin for blockdiag
Home-page: http://bitbucket.org/tk0miya/blockdiagcontrib
Author: Takeshi Komiya
Author-email: i.tkomiya at gmail.com
License: Apache License 2.0
Keywords: diagram,generator
Platform: UNKNOWN
Classifier: Development Status :: 4 - Beta
Classifier: Intended Audience :: System Administrators
Classifier: License :: OSI Approved :: Python Software Foundation License
Classifier: Programming Language :: Python
Classifier: Topic :: Software Development
Classifier: Topic :: Software Development :: Documentation
Classifier: Topic :: Text Processing :: Markup
Requires-Dist: blockdiag (>=1.4.0)
Requires-Dist: setuptools
